parc/__init__.py
parc/_parc.py
parc-0.40.dist-info/METADATA
parc-0.40.dist-info/WHEEL
parc-0.40.dist-info/top_level.txt
parc-0.40.dist-info/RECORD
