Metadata-Version: 2.1
Name: parc
Version: 0.40
Home-page: https://github.com/ShobiStassen/PARC
Author-email: shobana.venkat88@gmail.com
License: MIT
Requires-Dist: pybind11
Requires-Dist: numpy
Requires-Dist: scipy
Requires-Dist: pandas
Requires-Dist: hnswlib
Requires-Dist: igraph
Requires-Dist: leidenalg (>=0.7.0)
Requires-Dist: umap-learn
Provides-Extra: dev
Requires-Dist: pytest ; extra == 'dev'
Requires-Dist: scikit-learn ; extra == 'dev'
